[
    {
        "beatmap_id": "1626537",
        "score_id": "2654642979",
        "score": "9097324",
        "maxcombo": "704",
        "count50": "0",
        "count100": "3",
        "count300": "526",
        "countmiss": "2",
        "countkatu": "3",
        "countgeki": "127",
        "perfect": "0",
        "enabled_mods": "8",
        "user_id": "4452992",
        "date": "2018-10-17 20:33:31",
        "rank": "A",
        "pp": "328.653",
        "replay_available": "0"
    },
    {
        "beatmap_id": "795627",
        "score_id": "2637266974",
        "score": "42213808",
        "maxcombo": "1327",
        "count50": "0",
        "count100": "18",
        "count300": "980",
        "countmiss": "0",
        "countkatu": "13",
        "countgeki": "215",
        "perfect": "0",
        "enabled_mods": "8",
        "user_id": "4452992",
        "date": "2018-09-22 14:11:37",
        "rank": "SH",
        "pp": "319.362",
        "replay_available": "0"
    },
    {
        "beatmap_id": "819641",
        "score_id": "2641624759",
        "score": "43100877",
        "maxcombo": "1351",
        "count50": "0",
        "count100": "8",
        "count300": "1005",
        "countmiss": "0",
        "countkatu": "7",
        "countgeki": "192",
        "perfect": "1",
        "enabled_mods": "8",
        "user_id": "4452992",
        "date": "2018-09-28 19:18:40",
        "rank": "SH",
        "pp": "302.063",
        "replay_available": "1"
    },
    {
        "beatmap_id": "1554502",
        "score_id": "2641001549",
        "score": "46295647",
        "maxcombo": "1599",
        "count50": "0",
        "count100": "15",
        "count300": "1200",
        "countmiss": "1",
        "countkatu": "11",
        "countgeki": "433",
        "perfect": "0",
        "enabled_mods": "8",
        "user_id": "4452992",
        "date": "2018-09-27 20:41:06",
        "rank": "A",
        "pp": "298.608",
        "replay_available": "0"
    },
    {
        "beatmap_id": "1031604",
        "score_id": "2277290827",
        "score": "7093025",
        "maxcombo": "559",
        "count50": "0",
        "count100": "7",
        "count300": "392",
        "countmiss": "1",
        "countkatu": "6",
        "countgeki": "90",
        "perfect": "0",
        "enabled_mods": "8",
        "user_id": "4452992",
        "date": "2017-04-02 20:54:01",
        "rank": "A",
        "pp": "297.853",
        "replay_available": "1"
    },
    {
        "beatmap_id": "1608832",
        "score_id": "2584976489",
        "score": "4072403",
        "maxcombo": "436",
        "count50": "0",
        "count100": "2",
        "count300": "331",
        "countmiss": "0",
        "countkatu": "2",
        "countgeki": "59",
        "perfect": "1",
        "enabled_mods": "24",
        "user_id": "4452992",
        "date": "2018-07-16 18:48:54",
        "rank": "SH",
        "pp": "294.543",
        "replay_available": "0"
    },
    {
        "beatmap_id": "1046339",
        "score_id": "2297551395",
        "score": "12495189",
        "maxcombo": "724",
        "count50": "0",
        "count100": "1",
        "count300": "527",
        "countmiss": "0",
        "countkatu": "1",
        "countgeki": "107",
        "perfect": "1",
        "enabled_mods": "8",
        "user_id": "4452992",
        "date": "2017-05-08 22:21:22",
        "rank": "SH",
        "pp": "294.208",
        "replay_available": "0"
    },
    {
        "beatmap_id": "1619555",
        "score_id": "2641017161",
        "score": "4730402",
        "maxcombo": "470",
        "count50": "0",
        "count100": "4",
        "count300": "380",
        "countmiss": "1",
        "countkatu": "4",
        "countgeki": "129",
        "perfect": "0",
        "enabled_mods": "8",
        "user_id": "4452992",
        "date": "2018-09-27 21:11:03",
        "rank": "A",
        "pp": "291.939",
        "replay_available": "0"
    },
    {
        "beatmap_id": "1699366",
        "score_id": "3039457404",
        "score": "5714823",
        "maxcombo": "474",
        "count50": "0",
        "count100": "4",
        "count300": "415",
        "countmiss": "0",
        "countkatu": "3",
        "countgeki": "75",
        "perfect": "0",
        "enabled_mods": "8",
        "user_id": "4452992",
        "date": "2020-04-01 01:54:41",
        "rank": "SH",
        "pp": "291.348",
        "replay_available": "0"
    },
    {
        "beatmap_id": "1630299",
        "score_id": "2641024541",
        "score": "13115860",
        "maxcombo": "877",
        "count50": "0",
        "count100": "7",
        "count300": "599",
        "countmiss": "0",
        "countkatu": "5",
        "countgeki": "109",
        "perfect": "0",
        "enabled_mods": "8",
        "user_id": "4452992",
        "date": "2018-09-27 21:26:52",
        "rank": "SH",
        "pp": "289.724",
        "replay_available": "1"
    }
]